README.md
setup.py
bin/pynt-embed
bin/pynt-serve
codebook/__init__.py
codebook/foo.py
codebook/manager.py
codebook/node_transformers.py
codebook/syntax.py
codebook.egg-info/PKG-INFO
codebook.egg-info/SOURCES.txt
codebook.egg-info/dependency_links.txt
codebook.egg-info/not-zip-safe
codebook.egg-info/requires.txt
codebook.egg-info/top_level.txt