Metadata-Version: 1.1
Name: codebook
Version: 1.2.2
Summary: Emacs minor mode for generating and interacting with jupyter notebooks
Home-page: http://github.com/ebanner/pynt
Author: Edward Banner
Author-email: edward.banner@gmail.com
License: MIT
Keywords: interactive programming jupyter ipython emacs
Platform: UNKNOWN
Classifier: Development Status :: 3 - Alpha
Classifier: Environment :: MacOS X
Classifier: Programming Language :: Python :: 3.6
Classifier: Framework :: IPython
Classifier: Framework :: Jupyter
Classifier: Intended Audience :: Developers
Classifier: Intended Audience :: Developers
Classifier: Intended Audience :: Education
Classifier: License :: OSI Approved :: MIT License
Classifier: Natural Language :: English
Classifier: Operating System :: MacOS
Classifier: Topic :: Education
Classifier: Topic :: Software Development
Classifier: Topic :: Software Development :: Code Generators
Classifier: Topic :: Software Development :: Debuggers
Classifier: Topic :: Software Development :: Documentation
Classifier: Topic :: Text Editors
Classifier: Topic :: Text Editors :: Emacs
Classifier: Topic :: Text Editors :: Integrated Development Environments (IDE)
